{
    "2.0": "(... O que está acontecendo? A luz do sol está tão forte!?\nE dói demais quando bate na minha pele!)",
    "4.0": "Ainda é cedo.\nEu realmente vou voltar para casa agora?",
    "4.1": "Ainda tem um tempo antes do pôr do sol…\nEu vou mesmo voltar para casa agora?",
    "4.2": "Hoje está extremamente quente.\nTalvez seja melhor ir embora mais cedo...?",
    "4.3": "Ir para Casa\nAgora Não",
    "16.0": " \n ",
    "17.0": "Também tem um bilhete dentro…     \\w[30]\nNele estão escritas algumas palavras tão bagunçadas que são quase ilegíveis—",
    "17.1": "\\py[24]“Minha juventude jaz enterrada aqui dentro…”\n\\w[60]",
    "17.2": "(Isso parece tão…\ntão insuportavelmente pesado…)"
}