{
    "2.0": "—I can't do this anymore. \nI can't keep imagining things.\nI'm completely out of inspiration...",
    "2.1": "Continue the Delusion\nStop the Delusion",
    "2.2": "While sitting on the toilet, thoughts \nI'd never normally notice begin to flash through my mind.",
    "2.3": "Come to think of it, \neven the Great Sages started as ordinary humans.\nMaybe they too, while on the toilet just like this,\nattained an unprecedented level of focus—",
    "2.4": "\\{In other words, many of the world's truths\nwere actually conceived on the toilet!",
    "2.5": "Whew, it's all just a delusion.\nHow could a Great Sage be such a vulgar person...?",
    "2.6": "I spent some time killing time \nwith these idle thoughts on the toilet...",
    "2.7": "The universe was born from nothingness at the very beginning,\nbut what is the purpose of its existence?",
    "2.8": "What is the meaning of our existence as humans?",
    "2.9": "What is the meaning of life?",
    "2.10": "——I feel as if my consciousness is being transcended.",
    "2.11": "Oh, universe, please give me a sign.\nWhat is the ultimate answer to life, the universe, and everything?",
    "2.12": "(I close my eyes and accept the revelations from the cosmos—)",
    "2.13": "A thought suddenly appears in my mind.\nBut what on earth does this mean...?",
    "2.14": "God said, \"Let there be a little sister.\"\nAnd so, there was a little sister in this world.",
    "2.15": "In other words...\nShe is, therefore I am...",
    "2.16": "I am moved to tears of joy for having \ngrasped the ultimate meaning of life.",
    "2.17": "Hmm... life with \\str[120] lately has finally\nmade me realize some things I've been ignoring...",
    "2.18": "It's been a nerve-wracking journey, \nbut thankfully, she's grown up safely,\nand her constitution has finally stabilized...",
    "2.19": "As family, it really does feel quite rewarding.",
    "2.20": "\\{But...!        \\}\\w[40]\n\\str[120] is a girl after all, \nand her body is gradually developing.\n\\w[10]\nAs the only man in the house now, \nthese changes are... a bit too stimulating.",
    "2.21": "And besides, she walks around every day in those loose,\noversized pajamas, totally defenseless.\nEven though there are no outsiders, \nisn't she testing my self-control a bit too much—",
    "2.22": "Yes, that's exactly it!\nI'm glad she trusts me this much, of course...\nBut as her family, I have to hold the line and protect her properly!",
    "3.0": "\"Whew… that feels much better...\"",
    "3.1": "...So, what should I do next?",
    "3.2": "Look Around\nDaydreaming\nKill Time\nLeave",
    "3.3": "This cramped little space—what could possibly be hiding here...?    \\w[45]\nEven as I said that, I couldn’t help but start digging around.",
    "3.4": "\"Ooooh!! This is…!\"",
    "3.5": "——Toilet paper.",
    "3.6": "————A junk.",
    "3.7": "\"Well, I am in the toilet after all.\"",
    "3.8": "Feels like I wasted my time.",
    "3.9": "\"Hm? What was that sound?\"",
    "3.10": "It's a C.",
    "3.11": "A C snuck in from who-knows-where and zipped past my feet.",
    "3.12": "You bastard, showing yourself so boldly in front of me!    \\{\nTake this!",
    "3.13": "Bullseye. The C dropped dead on the spot.",
    "3.14": "\"Hmph, as expected of me...\"",
    "3.15": "Missed! \nStartled, the C quickly vanished without a trace.",
    "3.16": "\"Damn, that thing’s fast!\"",
    "3.17": "……This isn’t gonna work forever.\nMaybe it’s time to get some bug spray...",
    "3.18": "\"Hm? What was that sound?\"",
    "3.19": "…The sound’s gone. Was it just my imagination?",
    "3.20": "Can’t stay sitting here forever.\nI should probably head out—",
    "3.21": "\"Ah, we're all out of toilet paper—\"",
    "3.22": "Now I've really got nothing to do—",
    "3.23": "I tore off some toilet paper and tried to \nbraid it into a shape, but I failed miserably.",
    "3.24": "\"That's weird... \nit's never this hard when I'm tying \\str[120]'s hair...\"",
    "3.25": "...I feel like I'm just wasting my life.",
    "3.26": "Let's make a paper airplane—\nThinking that, I tore off some more toilet paper.",
    "3.27": "Because the paper was so soft, it took several \nfailed attempts before I finally managed to fold a paper airplane.",
    "3.28": "\\{\"Off it goes!\"",
    "3.29": "But the paper airplane plummeted straight down \nbefore it could even get very far...",
    "3.30": "Maybe I should try a paper crane—    \\w[40]\nI tore off some more paper,\nbut I just couldn't get the shape to look right...",
    "6.0": "\\nl< >\"————————！？\"",
    "6.1": "That was \\str[120]'s scream...! Don't tell me!?",
    "6.2": "\\{\"What happened!?\"",
    "6.3": "\\nl< >\"Waaaaaahhhhhh—!?\"",
    "6.4": "\\{So fast!?     \\w[25]\nEh...! What on earth is going on!?",
    "6.5": "\"There's nothing here...\"",
    "6.6": "\\nl< >\"Sob, sob... \\str[121]...\"",
    "6.7": "The sound is coming from inside the toilet...!\nNo time for hesitation—I threw open the door.",
    "6.8": "\\str[120] is shivering on top of the toilet seat. \nNaturally, she's wearing nothing from the waist down...\nI don't even know where to look...",
    "6.9": "Hm... so \\str[120] hasn't even started \ngrowing pubic hair down there yet..  \\w[25]\\^",
    "6.10": "No, no, now is not the time for these delusions!",
    "6.11": "\"...What happened here?\"",
    "6.12": "\\nl< >\"There is a C in the toilet...\"",
    "6.13": "C...!?\nThat thing again! \nHow dare it scare my precious \\str[120] to tears!",
    "6.14": "I searched the toilet thoroughly afterward, \nbut in the end, I couldn't find a single trace of the C.",
    "6.15": "After \\str[120] went into the toilet, \nI secretly crept up to the toilet door.",
    "6.16": "Quietly cracking the door open... \nI can't let \\str[120] notice me..",
    "6.17": "\\nl< >\"Mnya—\"",
    "6.18": "Oho, I can see everything perfectly...!\nSo \\str[120] has that sleepy look even when she's on the toilet.",
    "6.19": "\\nl< >\"..................?\"\n\\w[60]\\^",
    "6.20": "\\nl< >\"...Is something there?\"",
    "6.21": "\\nl< >\"..........................\"\n\\w[60]\\^",
    "6.22": "————Oh no!!\nI was so fixated on \\str[120] that I forgot the important thing...!\nWhat just appeared there is—      \\w[70]\\^",
    "6.23": "\\nl< >\"Waaaaaahhhhhh—!?\"",
    "6.24": "\\{As I thought, the C appeared—!",
    "6.25": "This time I burst into the toilet without a second thought, \nmy eyes instantly locking onto the scuttling C.",
    "6.26": "\\{\"So you're the one who made my \\str[120] cry!?\"",
    "6.27": "The slipper hit it right between the eyes.\nThe C dropped dead on the spot.",
    "6.28": "\"Whew... finally took that thing down...\"",
    "6.29": "\\nl< >\"Sob, sob... \\str[121]...\"",
    "6.30": "\"It's okay now. \n\\str[121] took care of the bad guy.\"",
    "6.31": "\\nl< >\"Ugh... \\str[121], don't leave,\nI'm still scared...\"",
    "6.32": "\".......Then I'll just stay here with my back turned.\"",
    "6.33": "\"....Hm? Uh... \nthen I'll just stand guard at the door.\"",
    "6.34": "To put \\str[120] at ease,\nI stood guard at the toilet door with \na serious face, like a sentry.",
    "6.35": "Waiting for \\str[120] to finish felt surprisingly long. \nOnce I calmed down, images of her pussy I just \nglimpsed started flashing in my mind.",
    "6.36": "There... was still no hair at all. \nSuddenly, I'm curious to see how \\str[120] is \nusing the toilet right now—\n\\w[30]\\^",
    "6.37": "No, no! I can't be having these thoughts \nat a time like this...!",
    "6.38": "............Maybe just one tiny peek?",
    "6.39": "Just one peek\nForget about it",
    "6.40": "Yeah... it would be bad if there were other C around!\nThis is strictly for \\str[120]'s safety—",
    "6.41": "I guess it's still not a good idea...\nI need to respect \\str[120]'s privacy...",
    "6.42": "\\nl< >\"................!?\"",
    "6.43": "Ah, I've been busted.",
    "6.44": "\\nl< >\"\\str[121], what are you doing?\"",
    "6.45": "\"Uh, I thought I heard another C, so————\"",
    "6.46": "\\nl< >\"I'm not scared anymore! \n\\str[121], get out!\"",
    "6.47": "And I got kicked out of the toilet...",
    "6.48": "\\str[120] was still trembling from the shock, \nand because of that, she didn't seem to notice \nthat I was tilting my head to steal a glance...",
    "6.49": "Oooohhhh... So that's how \\str[120] pees...\n\\w[45]\\^",
    "6.50": "\\>Wait, didn't I see this all the time \nwhen we were kids!?     \\w[30]",
    "6.51": "With the image of \\str[120]'s plump, smooth pussy \nburned into my mind, I silently turned my head away.",
    "6.52": "\\nl< >\"Whew... finally finished...\"",
    "6.53": "\\nl< >\"...\\str[121], you can come out now.\"",
    "9.0": "\\nl< >\"\\str[121]! Are you still in the toilet?\"",
    "9.1": "\"...I’ll be out in a second!\"",
    "9.2": "I’ve probably wasted too much time—better get going...",
    "21.0": "Just then, a familiar sound rang out.",
    "21.1": "\\{Wait...\\w[45] that sound—it's C!",
    "21.2": "\\nl< >\\{\"…………Huh?\"",
    "21.3": "\\nl< >\\{\"Aaaaahhhh—!!\"",
    "21.4": "\\str[120] has noticed C too!\nThis is bad! If C attacks in a situation like this,\nshe might faint from the shock!!",
    "21.5": "\\{\"……！\"",
    "21.6": "Before I could even think, my body moved on its own,\nand I rushed into the toilet at lightning speed.",
    "21.7": "\\{\"Are you the one who made my \\str[120] cry!?\"",
    "21.8": "Direct hit. The C is dead on the spot.",
    "21.9": "\\nl< >\"Uuuh... \\str[121]...\"",
    "21.10": "\"It’s okay now. \nThe bad thing is gone—\\str[121] took care of it.\"",
    "21.11": "\\nl< >\"Huh...?\n\\str[121]... your pants...\"",
    "21.12": "\"——————————Ah.\"",
    "21.13": "Since I was already worked up before barging \ninto the toilet. my cock was standing rock hard—\nso close to \\str[120]’s face…",
    "21.14": "Just as I was worrying, \nI noticed something strange in \\str[120]’s eyes,\nshe was fidgeting too.    \\w[60]\nCould that weird candy still be working?",
    "21.15": "\\str[120]’s expression started to look dazed,\nand then, out of nowhere, \nshe leaned in and took my cock into her mouth.",
    "21.16": "That bold move completely shattered my self-control. \nI put my hand on my \\str[120]’s head,\nand started guiding her to take my cock even deeper.",
    "21.17": "Even though she was pretty clumsy,\nthe warmth and softness of her mouth \nstill felt amazing.",
    "21.18": "From this angle, \nI could see \\str[120]’s wet pussy trembling slightly,\nlike something straight out of a dream.",
    "21.19": "Soon enough, \nthat urge to come started building up in waves—",
    "21.20": "Not wanting my \\str[120] to choke, \nI pulled my cock out of her mouth.",
    "21.21": "Right at that moment, a huge load of cum burst out, \nsplattering all over her face.",
    "21.22": "\\nl< >\"Ugh… it tastes awful…\"",
    "21.23": "\\str[120] stuck out her tongue playfully, \nbut I could tell she was still really shy.\nShe’d never do something this bold normally—\nit must be the effect of that candy.",
    "21.24": "But honestly, if it weren’t for that candy,\nI have no idea how things would’ve ended.",
    "21.25": "Afterward, we cleaned up the toilet together \nand went back to the bedroom,\nquietly acting like nothing had ever happened.",
    "22.0": "Sneaking around, sneaking around...",
    "22.1": "Hmm... I'm just worried \nif something's wrong with \\str[120]...\nI'll just take a quick look and leave...",
    "22.2": "Wait... what’s this!?",
    "22.3": "Caught \\str[120] jilling-off.    \\w[60]\nWhat’s going on… \nCould it be the effect of \nthe candy I gave her earlier!?",
    "22.4": "Though her technique still seems a bit clumsy,\nthe occasional nectar shows \nshe’s completely lost in the moment of joy.",
    "22.5": "Seeing \\str[120] trying so hard to feel good, \nI couldn’t help but want to step in and help her out…",
    "22.6": "Caught \\str[120] touching herself over her panties.    \\w[60]\nWhat’s going on… \nCould it be the effect of \nthe candy I gave her earlier!?",
    "22.7": "Maybe due to a lack of experience,  \n\\str[120] is clumsily rubbing her \npanties with her fingertips,  \nnot quite getting the hang of it.",
    "22.8": "Seeing \\str[120] trying so hard to feel good, \nI couldn’t help but want to step in and help her out…",
    "22.9": "But showing up now would definitely scare \\str[120],  \nhmm… yeah, it’s probably best to quietly step away.",
    "22.10": "Peek again!\nWalk away",
    "22.11": "Unable to resist the growing urge,\nI leaned closer to the crack in the door, \ncarefully watching.",
    "22.12": "Jack off\nBurst in!\nForget it",
    "22.13": "I'm starting to feel a little excited too... \nShould I join \\str[120]...?",
    "22.14": "This feels kinda risky… better not.\nIf I keep watching, this is gonna get awkward.\n I should slip out before my \\str[120] notices.",
    "22.15": "Since it's not the first time I've seen \nsomething like this, I just went with \nthe flow and tried to enjoy the moment.",
    "22.16": "While my \\str[120] was still lost in her own world, \nI quietly closed the door behind me.",
    "22.17": "\"Looks like \\str[120]’s finally at that age\nwhere she gets interested in this kind of stuff…\"\n \n \nFeeling a strange sense of sadness, \nI decided to just pretend I hadn’t seen anything…",
    "22.18": "The moment we both reached our peak,\nI let go completely and just came all over.",
    "22.19": "With a shiver running through her body,\n\\str[120] slowly stopped what she was doing and \nstarted breathing softly.",
    "22.20": "If I keep watching, this is gonna get pretty bad.\nBetter make my escape before \\str[120] notices.",
    "22.21": "Doing this kind of thing with \\str[120] feels so strange…\nBefore I knew it, my hand started matching her rhythm,\nand in that moment, \nit felt like our senses were somehow connected.",
    "22.22": "Watching \\str[120]’s fingers, I couldn’t help but imagine—\nwhat if it wasn’t her fingers touching her, \nbut my cock instead…?",
    "22.23": "As I got lost in that thought,\nit almost felt like I could really feel how soft \n\\str[120]’s pussy would be…\nImagination really is a scary thing.",
    "22.24": "I wonder what it would feel like to \nget as close as my \\str[120]’s fingers,\nstroking myself right up against her pussy…",
    "22.25": "I start picturing the tip of my cock pressing against \nmy \\str[120]’s tightly closed pussy, slowly spreading \nher open as I push, revealing the wet inside. My cock \ngets slick too, a lewd strand stretching between us…",
    "22.26": "The excitement I feel with her is nothing like \nwhen I’m alone. As I lose myself in these fantasies, \nthe guilt in my heart just turns into fuel,\nbringing me wave after wave of pleasure.",
    "22.27": "\\str[120] looks like she’s about to come, \nand I can’t help but speed up my own movements too.",
    "22.28": "\\{Ugh, I can’t hold it anymore…!",
    "23.0": "With what happened last time, \nI decided to just boldly barge into the toilet.",
    "23.1": "\\nl< >\\{\"…O-\\str[121]!?\"",
    "23.2": "\\nl< >\"…\\str[121],\nwhy did you come in here too…?\"",
    "23.3": "Her tone sounded a bit scolding, but judging from her \ndazed expression and the fact that she wasn't trying \nto kick me out, it seemed like I was in the clear.",
    "23.4": "I quietly moved to stand next to my \\str[120], my cock \njust a few centimeters away from her. She kept going \nwith her own hand, leaned in a little closer to me,\nand started licking me with her tongue.",
    "23.5": "\\str[120]’s slender tongue slithered around the tip of \nmy cock like a little snake, the warm, \nticklish sensation making me tremble uncontrollably.",
    "23.6": "We stayed like that in silence for a while, \nand I could feel myself getting close to the edge…\n\\str[120] must’ve noticed the way my cock was twitching,\nbecause she started moving her hand even faster.",
    "23.7": "Finally, as that unstoppable rush of release built up, \nmy cum started to shoot out.  \\w[60]\nThe moment the first spurt landed on \\str[120]’s face, \nshe suddenly took my cock into her mouth.",
    "23.8": "As she sucked, my \\str[120] kept teasing the tip with \nher tongue right where the cum was pouring out.\n \n \nThat unexpected gentleness and soft warmth completely \nbroke my self-control, and my cock just unloaded\nthe rest of my cum straight into her mouth.",
    "23.9": "Afterward, we cleaned up the toilet together,\nand when we got back to the bedroom, \nwe both pretended like nothing had ever happened."
}