{
    "3.0": "…\\str[120] is still sound asleep. \nWhat should I do?",
    "3.1": "Wake her up\nPat her head\nLeave her be",
    "3.2": "The Elixir Rubrum seemed to have improved \n\\str[120]'s condition, but I couldn’t help \nworrying that the effects might only be temporary.",
    "3.3": "I gently rubbed \\str[120]'s cheek. Maybe it \ntickled a little, she immediately made a face like \nshe was trying hard to endure it.",
    "3.4": "\\nl< >\"Mmm... hmm…\"",
    "3.5": "\"It's morning already. Think you can get up?\"",
    "3.6": "Because of her condition, \\str[120] always has \ntrouble waking up in the morning,\nmaybe I shouldn't force her to get up…?",
    "3.7": "Keep trying\nLeave her be",
    "3.8": "\\nl< >\"Mnyaa…\"\n\\nl< >\"—\\str[121]…\"\n\\nl< >\"Mmm… mmhm…\"",
    "3.9": "She just murmured a little and kept right on sleeping.\nThis kind of thing can't be rushed. \nBetter let her sleep a bit longer…",
    "3.10": "I gently patted her head.",
    "3.11": "…Guess it's time to start getting breakfast ready.",
    "4.0": "\"How are you feeling? \nYou're not pushing yourself too hard, are you?\"",
    "4.1": "\\nl< >\"Mnyaa… \\w[180]I'm fine yiiiiii——\"\\w[30]\\^",
    "4.2": "\"Careful!\\w[45] Seriously,\\w[45]\nyou’re clearly still half-asleep, aren’t you?\"",
    "4.3": "\"Hey~ still not fully awake?\nThen \\str[121]’s gonna get serious~!\"",
    "4.4": "\\nl< >\"Mmmmmm…\"",
    "4.5": "\"Here we go———\"",
    "4.6": "\"Feeling more awake now?\"",
    "4.7": "\\nl< >\"Uweh… there’s… so many of you, \\str[121]…\"",
    "4.8": "\"If you're still not feeling well, \ntry washing your face first.\"",
    "4.9": "\\nl< >\"Just carry me over… \\str[121]…\"",
    "4.10": "Yikes, maybe that prank went a little too far…\n\\str[120] still looks super dizzy.",
    "4.11": "\"Spin spin spin spin spin spin spin~!\"",
    "4.12": "\\nl< >\"Roll roll roll roll roll roll roll~!\"",
    "4.13": "\\nl< >\"Uweeeeh~~~~\"  \\w[120]",
    "4.14": "Dizzy and dazed, \\str[120] flopped back onto the bed...\nHuh? Did I maybe take the prank a bit too far?",
    "4.15": "Seeing that she didn’t even have the strength to \nget up, I had no choice but to give up \nand stop pushing her.",
    "4.16": "\"…Guess it’s time to start making breakfast.\"",
    "6.0": "So spicy... it hurts...",
    "6.1": "\\nl< >\"Uuuu... my mouth is so spicy... \nit hurts... uuuu...\"",
    "6.2": "\\str[120] was lying on the bed, \nsuffering from the spiciness,\nI need to quickly do something for her...",
    "6.3": "Pat her head\nPat her butt\nPrepare a drink",
    "6.4": "I gently patted \\str[120]’s head,\nwondering if this would make her feel any better...",
    "6.5": "\\nl< >\"Uuuu... now my head feels like it hurts too...\"",
    "6.6": "\\nl< >\"Ue e e...\"",
    "6.7": "Doesn’t seem to have any effect...",
    "6.8": "I gently patted \\str[120]’s butt,\nwondering if this would make her feel any better...",
    "6.9": "\\nl< >\"Uuuu... \\str[121]...\"",
    "6.10": "\\nl< >\"Uee... now my butt hurts too...\"",
    "6.11": "I hurriedly searched around and finally \nfound a bottle of \\ii[\\v[85]]!",
    "6.12": "\"Here’s \\ii[\\v[85]], \ndo you want to drink it...?\"",
    "6.13": "\\nl< >\\{  \"I want it!!\"",
    "6.14": "\\str[120] gulped down \\ii[\\v[85]] in one go...",
    "6.15": "I hurriedly searched around, but it seemed \nthere weren’t any drinks left at home...\nWith no choice, I prepared a glass of water for her.",
    "6.16": "\\str[120] gulped down the glass of water in one go...",
    "6.17": "\\nl< >\"Uuuu... my mouth still hurts...\"",
    "6.18": "\\nl< >\"Finally feeling a bit better... \nbut my tongue is still numb.\"",
    "6.19": "\\nl< >\"Chili peppers really are the enemy...\"",
    "6.20": "Looking at her slightly swollen lips, \nI started having some strange thoughts——",
    "6.21": "Oral check",
    "6.22": "\\nl< >\"Ehh... no, that’s kinda embarrassing...\n\\str[121] will smell something weird!\"",
    "6.23": "\\str[120] refused the oral check. \nMaybe my request really was too weird...",
    "6.24": "Anyway, I’m glad she’s feeling better,\nI need to be careful not to make food \ntoo spicy next time...",
    "6.25": "\"It’s fine! I’m just worried about you!?\nIt’s just a normal check!\"",
    "6.26": "\\nl< >\"A c-check, huh?\"",
    "6.27": "Under my intense gaze, \\str[120] blushed even deeper,\nbut her eyes were filled with gentleness and curiosity,\nand a faint hint of anticipation appeared \non her rosy cheeks.",
    "6.28": "\"Yeah, it’d be bad if blisters formed in your mouth!\"",
    "6.29": "\\nl< >\"I get it... then...\nyou can only look, okay? Don’t do anything weird...\"",
    "6.30": "\\nl< >\"Ah, ahh———\"",
    "6.31": "\\str[120] didn’t resist anymore, \nobediently standing in front of me,\nslowly tilting her head up and opening her small mouth,\nher little tongue shyly sticking out.",
    "6.32": "Maybe because she ate too much spicy food, her tongue \nlooked especially bright red, trembling slightly, \nwith saliva overflowing from the strong spiciness,\nclear droplets trailing down her soft lips.",
    "6.33": "She seemed both embarrassed and dazed,\nher eyes misty with tears, I couldn’t tell \nif she was still in pain from the spiciness.",
    "6.34": "\\nl< >\"\\str[121]——— are you done yet?\"\n\\w[150]",
    "6.35": "Oral treatment!",
    "6.36": "Seeing such a soft and tempting sight, \nI swallowed unconsciously, a surge of uncontrollable \ndesire welling up in my chest.",
    "6.37": "\"I will help you feel better, okay? \nIt’ll stop hurting soon...\"",
    "6.38": "\\nl< >\"—————Eh?\"",
    "6.39": "Almost like trying to convince myself,\nI leaned closer to \\str[120]’s face,\nand stuck out my tongue to gently touch her soft, \ndelicate little tongue, slowly and tenderly licking it.",
    "6.40": "The moment our tongues touched, she flinched slightly.\nShe seemed shy and confused by my actions, \nbut didn’t avoid or resist, still staring at me \nwith those big watery eyes, full of curiosity.",
    "6.41": "Tasting her tender tongue and the sweetness \nin her mouth, I completely forgot my original \npurpose, the sensation of her tongue and the \nwarmth of her mouth weaving a powerful pleasure,\nmaking my actions bolder and greedier as \nI sought more and deeper of her sweet breath.",
    "6.42": "Her little tongue seemed to gradually adapt to \nmy movements, even starting to respond slightly,\nher gentle and shy cooperation hinting at \na subtle sense of anticipation and attachment.",
    "6.43": "\\nl< >\"Mmm... haa, \\str[121]...\"",
    "6.44": "I didn’t know how long it lasted, \nbut \\str[120] began to run out of breath,\nher fingers lightly pressing against my chest \nas she let out muffled moans,\nuntil her little face turned even redder from \nlack of oxygen, and only then did I reluctantly \nlet go of her mouth.",
    "6.45": "\\nl< >\"Haa... haa...\"",
    "6.46": "\\nl< >\"Mmph, \\str[121]! \nYou said it was just a check...!\"",
    "6.47": "Even though her words carry a spoiled complaint,\nher expression didn’t really look like she \nwas scolding me, but more like she was being playful.",
    "6.48": "\"Sorry, sorry, I’ll be careful next time...\nbut, doesn’t your tongue feel better now?\"",
    "6.49": "\\nl< >\"Eh...? Mmm, yeah...\"",
    "6.50": "\\nl< >\"No...! That’s not the point! \n\\w[160]\\^",
    "6.51": "\\nl< >\\{\nYou’re such an idiot, \\str[121]!\"",
    "6.52": "\\str[120] ran away.",
    "6.53": "I watch her shy and flustered figure as she runs off,\nMy tongue still tingling with the sweet and \nwet sensation from earlier,\n \na strong pleasure mixed with an indescribable sense \nof taboo swirling deep inside,\nrefusing to fade away...",
    "7.0": "Hmm... I'm starting to get a little hungry. \nIt's about time to make dinner.",
    "7.1": "\"Hey, it’s evening already. \nTime to wake up, sleepyhead.\"",
    "7.2": "\\nl< >\"Mmnn—\\w[60]just let me sleep for one more hour...\"",
    "7.3": "\\str[120] is still lazily lying in bed, refusing to move.\nOh dear, I guess there’s no helping it then…",
    "7.4": "\"Oh, by the way, \nthere's freshly fried hamburger steak tonight—\"",
    "7.5": "\\nl< >\"Ugh... I'm so sleepy—\"",
    "7.6": "\\nl< >\"But where's the hamburger steak!? \nWhere is it!?\"",
    "7.7": "\"Sorry, that was something \nyou could only see in your dreams—\"",
    "7.8": "\\nl< >\"Ehh... seriously!? That’s so mean, \\str[121]!\"",
    "5.0": "I followed \\str[120] into the living room. The TV was already on,\nand she was curled up in the center of the sofa like a baby bird \nwaiting for its nest, hugging her knees and staring \nintently at the screen.",
    "5.1": "What kind of anime could she be so into…? Since I’m never \nhome during the day, I don’t really know what she usually watches,\nbut seeing her so excited for once made me curious too,\nso I ended up sitting down on the sofa and looking at the TV.",
    "5.2": "\\{\\c[27]“Starlight Magical Girl Ruby!”\nEpisode 1! \nAn Ordinary Girl and a Miracle of the Stars! \nThe Contract Begins!",
    "5.3": "\\c[27]Ruby is an average girl—average grades, bad at sports, and zero magical talent—\nbut one day on her way home, she’s chased by a monster and runs into a dead end!\nIn her moment of despair, the mysterious star spirit 'Noa' appears, \nawakened by her will to survive! 'I want to live!' she cries—and in that moment, ",
    "5.4": "\\c[27]starlight bursts forth—the contract of fate is sealed!\nHer first transformation! Driven by instinct, she fights back and repels the monster!\nLooking at her hands glowing in the starlight, \nRuby is speechless: 'Is this… me?'",
    "5.5": "\\nl< >\"She transformed! That was amazing—! \nAnd Noa is so cute! The starlight is so pretty!   \\w[120]\nLook, \\str[121]! Ruby-chan couldn’t do anything before!\nBut in the end, she was chosen to become a magical girl!\"",
    "5.6": "\"Ah, yeah…\"",
    "5.7": "……………………\n……………………",
    "5.8": "She... transformed just like that?! \nAnd the fight’s already over?\nA monster contract is supposed to be life-threatening…\nIsn’t letting a kid handle this gonna get the guild in trouble…?",
    "5.9": "I stared at the TV with a serious expression, full of confusion.\nBut when I glanced at \\str[120]’s wide eyes and open mouth, \nfilled with admiration, I decided to just keep quiet.",
    "5.10": "\"Yeah, the visuals are flashy. As long as you’re enjoying it…\"",
    "5.11": "I didn’t really get the plot,\nbut I enjoyed some quiet viewing time with \\str[120]!",
    "5.12": "Last episode felt like a total mess…\nBut \\str[120] loves it, so I guess it’s not some weird anime?   \\w[60]\nNo! I can’t just judge it from a few scenes!\nThinking that, I sat back down on the sofa and looked at the TV again.",
    "5.13": "\\{\\c[27]“Starlight Magical Girl Ruby!”\nEpisode 2! \nSpecial Training Begins! \nMagic Mayhem Unleashed!",
    "5.14": "\\c[27]Special training begins!\nNoa’s custom star-powered lessons push Ruby to the limit!\nAfter falling off the roof 37 times, she finally manages to transform on \nher own—but her magic goes out of control!\n\\c[27]The school hallway turns into a disaster zone, shop signs \nin town explode like fireworks! With citizens complaining and \nsecurity stepping in, can the weakest magical girl in history\nreally turn things around under Noa’s brutal training?!",
    "5.15": "\\nl< >\"Ahh… poor Ruby…    \\w[90]\nShe must be so frustrated… She just got her powers, \nand she’s not used to them yet.\"",
    "5.16": "\"Yeah, it’s definitely hard to watch…\"",
    "5.17": "Isn’t this… basically child labor abuse…?\nAnd this star spirit Noa too…\nHow did they ever form successful contracts like this \nin the past…?",
    "5.18": "Not wanting to ruin \\str[120]’s viewing experience,\nI just silently grumbled in my mind—",
    "5.19": "\\{\\c[27]“Starlight Magical Girl Ruby!”\nEpisode 3! \nThe First Clash of Flame and Stardust!",
    "5.20": "\\c[27]The mysterious transfer student Reina makes a strong entrance!\nHer flame magic completely overwhelms Ruby’s clumsy starlight!\nBehind her cold stare lies a painful past—\nWhen the hesitant newbie meets the battle-hardened warrior!\n\\c[27]Their clashing ideals explode when monsters attack!\nCan starlight and fire really work together?!",
    "5.21": "\\nl< >\"Reina’s scary… but she’s so strong!   \\w[90]\nStill, Ruby needs a partner like her, right?      \\w[90]\nThey’ll become good friends, won’t they?\"",
    "5.22": "Yeah, Reina is pretty cool…\nShe’ll definitely be a dependable senior.”",
    "5.23": "I nodded along with \\str[120],\nwatching the flashy fight scenes and clever animation in the new episode—\nTo be honest, I was starting to get hooked too.",
    "5.24": "I’m kinda looking forward to the next episode now!\nHad a nice quiet time watching anime with \\str[120]!",
    "5.25": "I started just watching casually, \nbut ended up going through several episodes without noticing…\nThe pacing’s a bit chaotic, but the setting is surprisingly interesting.   \\w[60]\nSeeing \\str[120] so into it—I think I’m starting to get it.\nWhat’s going to happen next…? \nI leaned back on the sofa, \ndrawn to the screen without even realizing it.",
    "5.26": "\\{\\c[27]“Starlight Magical Girl Ruby!”\nEpisode 4! \nDark Whispers Beneath the Festival Lights!",
    "5.27": "\\c[27]The school festival kicks off with a bang! \nRuby and Reina are forced to run a booth together!\nCotton candy machine explosion! Fortune-telling crystal ball shattered!\nThe worst duo is born! But strange whispers in the corner catch Noa’s attention—\n\\c[27]In those hollow eyes… an ominous black mist swirls!\nAs fireworks light up the sky, a lurking shadow begins to spread!\nWhat secrets are hiding beneath the festival’s cheerful surface?!",
    "5.28": "\\nl< >\"The school festival looks so fun!     \\w[90]\nRuby and Reina seem to be becoming friends too…!\"",
    "5.29": "\"It’s pretty fun, yeah…  \\}\nBut let’s be real, their relationship’s totally falling apart…\"",
    "5.30": "\\{\\c[27]“Starlight Magical Girl Ruby!”\nEpisode 5! \nThe Harsh Truth Behind the Scorching Past!",
    "5.31": "\\c[27]A sudden investigation into the black mist incidents! \nReina shows hostility toward the victim?! In the depths of an \nabandoned chapel, the claw marks of a heart-corrupting demon reopen \nher memories— Flame magic spirals out of control! \n\\c[27]Charred dolls and broken picture frames rise in the fire!\n'My town… this is how it turned to ashes!' Reina screams the truth, tears \nstreaming down her face! And at that moment—another heart-corrupting demon\nawakens beneath the school! Old wounds not yet healed… are about to be torn open again?!",
    "5.32": "\\nl< >\"How could this happen… \nI had no idea Reina-chan had that kind of past…     \\w[90]\n\\str[121], what’s gonna happen to them next…?\"",
    "5.33": "\"I-It’s gonna be fine! They still have magic, right!?\nMaybe Ruby will get her big moment next episode!?\"",
    "5.34": "I waved my arms around, trying to comfort \\str[120].\nWait, isn’t this supposed to be a story about the \nbeautiful bonds of friendship between girls!? But the plot’s heating up—\nthere’s gotta be an epic comeback scene coming soon, right!?",
    "5.35": "Totally hyped for the next episode!\nShared a tense but exciting anime-watching moment with \\str[120]!",
    "8.0": "When I got to \\str[120]’s room,\nI found her lying on the floor like a \ndried-up salted fish, completely listless.",
    "8.1": "The sweltering heat outside had clearly \nseeped into the house, the air scorching as it hit me.",
    "8.2": "This can’t go on, I have to \nthink of a way to help \\str[120] beat the heat…!",
    "8.3": "I scrambled to take care of \\str[120], \nwho was on the verge of heatstroke,\nuntil the sunset painted the sky red \nand she finally started to recover…",
    "8.4": "We both licked our popsicles desperately, trying to cool down,\nbut with waves of hot air hitting us, \nwe still ended up drenched in sweat.",
    "8.5": "\\str[120] feeling so uncomfortable she forgot her shyness, \nkept lifting her shirt hem, trying to create a bit of breeze.",
    "8.6": "\\nl< >\"It’s so hot… I just want to take a bath…\"",
    "8.7": "Let’s Go Together!\nLet’s Go!",
    "8.8": "\\nl< >\"No way, it’s too hot to be crammed together like that!\"",
    "8.9": "\\nl< >\"Geez! Don’t joke around at a time like this!\"",
    "8.10": "Yeah, it is summer after all…\nbut still, it feels a little lonely…",
    "8.11": "Because it was so hot, \\str[120] and I took turns bathing,\nbut not long after we finished, we were sweating again,\nand we kept this up all the way till evening…",
    "8.12": "Sneaking…\nSneaking…\nI tiptoed to the doorway of \\str[120]’s room.",
    "8.13": "\"Staaare————  \\w[60]\nW-what!?\"",
    "8.14": "I thought \\str[120] was taking a nap,\nbut instead she was lounging comfortably in front of the fan.",
    "8.15": "She must’ve thought no one was home and let herself fully relax,\ncompletely unaware how defenseless her posture looked to others.",
    "8.16": "She must’ve thought no one was home and let herself fully relax,\neven taking off her panties.",
    "8.17": "After feasting my eyes for a moment, \nI felt too embarrassed to keep watching,\nso I quietly left and went back to the entrance.",
    "8.18": "Once I set up the electric fan, \nthe air in the room immediately began to circulate, \nturning cool and refreshing.",
    "8.19": "\\nl< >\"Ohhh—so cool, it feels amazing~!\"",
    "8.20": "\"Come on, don’t sit right in front of the fan like that! \nYou’ll catch a cold!\"",
    "8.21": "\\str[120] gnawed on her popsicle while sitting in the breeze, \nlooking absolutely thrilled.",
    "8.22": "After quickly finishing a popsicle, \nI felt my body temperature drop noticeably.\n \n \nEven though the cicadas outside kept droning \nand the waves of heat continued to roll in,\nat least it no longer felt like I was about to be roasted alive…",
    "8.23": "But \\str[120] still didn’t seem cool enough,\nand lazily sat on the floor, enjoying the fan in comfort.",
    "8.24": "For a girl, that posture was a little too unreserved,\nI wanted to remind her, but instead my attention \nwas stolen by the unintentional glimpse of fanservice.",
    "8.25": "\\{Well, it is summer after all!!",
    "9.0": "Feeling a bit bored…\nI want some watermelon~",
    "9.1": "\\nl< >\"It’s so hot… I really want a bath…\"",
    "9.2": "\\nl< >\"\\str[121]… do you want a popsicle?\"",
    "9.3": "Chat\nSkinShip\nOffer Cola\nFeeling Sleepy",
    "9.4": "\\nl< >\"It’s still so hot…\nAt times like this, a nap is the best choice~\"",
    "9.5": "Yeah, by evening the sun won’t be so harsh anymore…",
    "9.6": "I napped with \\str[120] in the cool breeze until dusk.",
    "9.7": "Turns out there’s still that big bottle of cola from \nthe weird vending machine in the fridge.\nWith weather this hot, \\str[120] would definitely \nbe happy to drink it, right?",
    "9.8": "\\nl< >\"\\{Cold cola!?         \\}\\w[60]\nI want it! I want it!\"",
    "9.9": "Sure enough, \\str[120] looked delighted,\nso what should I do—",
    "9.10": "Shake It\nHand It Over",
    "9.11": "This seems to be a special cola with extra carbonation,\nif I shake it a little…",
    "9.12": "Thinking that, \nI couldn’t resist secretly giving the bottle a shake,\nthen handed it to \\str[120]…",
    "9.13": "\\str[120] was, of course, \nsprayed right in the face by the cola bursting out,\nand afterward, she made me ‘pay for it’ by forcing me to \nchug most of the bottle too.",
    "9.14": "In the end, she downed almost the whole bottle in one \ngo with an exaggerated appetite…\nher belly visibly swelling up.\nI-is this… really okay!?",
    "9.15": "Since she was soaked in cola, \nby the time she finished bathing and changing,\nthe sky was already turning to dusk.",
    "9.16": "\\nl< >\"Uwaaahhh—mmmmmffff!!\"",
    "9.17": "Maybe because of past experiences, this time she reacted instantly,\ninstinctively pressing her mouth to the bottle to try \nand stop the fizz from bursting out.",
    "9.18": "But this cola was just too fizzy,\nher small mouth couldn’t fully seal the opening,\nand bubbles kept escaping from the corners of her \nlips and along her cheeks…",
    "9.19": "In the end, she wound up like a clumsy little hamster,\nher face completely covered in cola spray.",
    "9.20": "\\nl< >\"\\w[121], your way of patting is \ntoo rough! No way!\"",
    "9.21": "Lewd Topics\nSummer Topics",
    "9.22": "\"Wouldn’t it feel cooler if you took it off?\"",
    "9.23": "I made that suggestion to \\str[120]…\nyeah, this really isn’t a weird idea…",
    "9.24": "\\nl< >\"Eh… but, I still feel kind of embarrassed…\"",
    "9.25": "Of course, she turned me down.\nHmm—looks like I’ll have to take the lead myself—",
    "9.26": "\"…Can I get a little closer and smell you?\"",
    "9.27": "Seeing the sweat glistening on her neck, \nI couldn’t help but ask.",
    "9.28": "\\nl< >\"What? I’m all sweaty—it’ll smell gross!\"",
    "9.29": "\"No, no, \\str[120] definitely smells nice!\"",
    "9.30": "\\nl< >\"Geez, there’s no way that’s true!\"",
    "9.31": "\"Then I'll let you sniff me in return——\n\\w[30]\\^",
    "9.32": "\\nl< >\"No way! \\str[121], \nyou’re definitely smelly.\"",
    "9.33": "\\{\n\"Ugh…!\"",
    "9.34": "And just like that, I was flat-out rejected.",
    "9.35": "Caught up in the summer heat, \nI chatted with her about all sorts of lewd topics,\nbut it was still so hot!",
    "9.36": "\\nl< >\"The sound of cicadas… sometimes it’s really noisy…\"",
    "9.37": "Well, it is summer after all.",
    "9.38": "\\nl< >\"It feels like everyone eats watermelon this season,\nI kinda want to try it too~\"",
    "9.39": "Hmm… watermelon, huh… where could I even get one?",
    "9.40": "\\nl< >\"At times like this, popsicles are still the best!\n\\w[120]\\^",
    "9.41": "\\nl< > Ughhh… my head hurts…!      \\w[60]\nBut it feels so good!\"",
    "9.42": "Eh… just how many did she eat…?",
    "9.43": "\\nl< >\"Is there even a difference between in the ocean and in a bathtub?\nI totally don’t get it…\"",
    "9.44": "Oh, right—she’s never seen the ocean before.\nIs there some way I could let her experience \nwhat it’s like at the seaside…",
    "9.45": "Caught up in the summer heat, \nI chatted with her about all sorts of summer topics,\nbut it was still so hot!",
    "10.0": "\\{\\c[27]Welcome to Episode 54 of \nBunny’s Gourmet Showdown!\nToday’s theme is—\nhow to make an irresistible super juicy meat burger!",
    "10.1": "\\{\\c[27]Now let’s welcome our lovely Maid Bunny,\nwho’s going to show us her amazing cooking technique!",
    "10.2": "\\{\\c[27]Huh!? That was way too fast!\nMaid Bunny has already—finished it!!\nBehold, the legendary—Instant Delicious Meat Burger!!",
    "10.3": "\\{\\c[27]And that’s all for today’s show!\nThanks so much for tuning in\nsee you next time!",
    "10.4": "What… is this?\nI don’t understand a single word…",
    "10.5": "Ah… it’s already over.",
    "10.6": "Oh, the weather forecast is on right now...\nLet's see what the weather will be like tomorrow—",
    "10.7": "But at least I can understand the images,\nbetter not overthink it.",
    "10.8": "Looks like tomorrow will be sunny.\nI just hope it won't be too hot at noon...",
    "10.9": "Looks like tomorrow will be cloudy.\nIt's great that it's cooling down—",
    "10.10": "Looks like tomorrow will be rainy.\nPerfect, I'll go to the river and \nsee if I can catch some fish.",
    "10.11": "Looks like tomorrow will be an especially hot sunny day...\nIs that temperature really okay!?",
    "10.12": "Oh, a cooking show is on right now...\nI wonder what new recipes I can learn—",
    "10.13": "What is this...?\nI feel like I didn't learn anything...",
    "10.14": "Oh, the news is on right now...\nHas anything major happened recently?",
    "10.15": "It feels like something incredible has happened \nin the Abyss—",
    "10.16": "After drinking a bottle of Elixir Rubrum, \n\\str[120] isn't as prone to drowsiness as usual,\nso it's a rare opportunity to watch \nlate-night programs together with her.\nI wonder what interesting content will be on at this time~?",
    "10.17": "Although I didn't get to see the program \nI wanted to watch before, just in case,\nI came to the living room with \\str[120] again \nduring the late-night time slot.",
    "10.18": "Maybe it just happened to be no programs \non that one day...",
    "10.19": "But after turning on the TV,\nthere was still only the silent static screen with no signal.",
    "10.20": "As expected, it doesn't work.\nIs there any way to watch interesting programs even late at night?\nMaybe I should ask around.",
    "10.21": "After sitting down with \\str[120], \nI turned on the TV with the remote.    \\w[60]\nBut the result was only a static screen with no signal...",
    "10.22": "There don't seem to be any programs on at this time, \nwhich is somewhat disappointing...\nIs there any way to watch interesting programs even late at night?\nMaybe I should ask around.",
    "10.24": "Ah—come to think of it, didn't I get a videotape before!?\nThis is the perfect time to take it out and watch it!",
    "10.25": "Hmm... although it's a bit late to say this now,\nthis videotape looks a bit ominous?   \\w[30]\nIt has an eerie atmosphere...!",
    "10.26": "Whatever, I'm free anyway,     \\{\nlet's put it on!",
    "10.27": "Huh~?        \\w[50]\nThe atmosphere feels pretty realistic...\nIs it some kind of documentary?",
    "10.28": "...Eh?\nThis is... actually a horror movie?",
    "10.29": "\\nl< >\"Ee——————————\"\n\\w[30]\\^",
    "10.30": "\\nl< >\"Eeeeaaaaahhhhh\naaaaahhh—————————\"",
    "10.31": "Just as I was regretting buying the wrong videotape,\n\\str[120] had been pressed close to me, suddenly let out a scream,\nand in the next instant, my vision was swallowed by darkness.",
    "10.32": "\\{\"Eh—what's wrong—!?\nWhat happened—!?\"",
    "10.33": "At the same time, a suffocating pressure also swept over me,\nI flailed my arms in panic, struggling,\nonly then did I suddenly realize—\nsomething incredibly soft was clinging tightly to my body.",
    "10.34": "Just as I was regretting buying the wrong videotape,\n\\str[120] sitting not far away jumped up in \nfright and quickly ran away—",
    "10.35": "This is not good...\nI hope this won't leave any psychological trauma for \\str[120]...",
    "10.36": "In the end, \nit took quite a bit of time to finally calm \\str[120] down.\nI just hope this accident won't leave \nany lasting shadow in her heart...",
    "10.37": "${$dataItems[189]?.name}\n${$dataItems[188]?.name}",
    "11.0": "\\str[120] startled by the horror scene, jumped up and clung tightly to me...\nNo, more precisely—she locked her arms around my neck in a chokehold!",
    "11.1": "Th-this girl! Where did she get such monstrous strength!?   \\w[30]\nI can't... break free at all!!    \\w[30]\nThis is bad...! I... I can't... breathe...!?",
    "11.2": "\"\\str[120]... d-don't be scared... \\w[30]\nWait, first... let go... I... can't breathe...\"",
    "11.3": "\\nl< >\"Uwaaaaaah...!\nThe movie... it's so scary...!\"",
    "11.4": "I don't know how much time passed, \nbut \\str[120] finally stopped her violent reaction just before I suffocated,\nthough she continued to cling to me like a koala, \nrefusing to get down.",
    "11.5": "\"It's okay now... I've already turned off the TV.\"",
    "11.6": "\\nl< >\"Mmmmm...!\"",
    "11.7": "I wanted to tell \\str[120] it was safe to turn around now,\nbut she still refused to let go no matter what.",
    "11.8": "This is a bit troublesome... Due to never leaving the house,\n\\str[120] has been afraid of unknown creatures and ghosts since childhood.\nEven I was startled by that horror scene just now,\nso it's not hard to understand why she's like this...",
    "11.10": "How should I calm \\str[120] down now...\nSince she's locked onto me completely, \nall I can do with my barely movable hands is gently pat her back, \nhoping that will help her relax a little.",
    "11.11": "But as I gradually calmed down myself,\nI couldn't help but become aware of some new problems...",
    "11.12": "Because we're pressed so close together, \nthrough that thin layer of fabric,\nI can clearly feel the warmth radiating from \\str[120].\nAnd that undeniable, soft sensation of her chest...\nAs for the faint fragrance drifting from her hair, \nit keeps wafting into my nose, making it impossible to stay calm.",
    "11.13": "Even though this isn't the right atmosphere for such thoughts,\nI'm gradually feeling my body temperature rising.      \\w[40]\nI need to separate from her before \\str[120] notices...!",
    "11.14": "\"I-I'll go make you some warm milk!\"",
    "11.15": "\\nl< >\\{\"No! Don't go!\"",
    "11.17": "\\str[120] buried her face deeper, \nletting out muffled sounds through her nose, \nher legs wrapping around me even tighter.\nWith this movement, her intimate area pressed right against my lower body.",
    "11.18": "My already semi-erect member instantly stiffened, \npressing against the center of her shorts through the fabric.\nThrough the thin material, I could even feel \nthe faint warmth and moisture seeping through.",
    "11.19": "This is bad, I can't let this continue...!\n\\str[120] is still so anxious, yet I'm getting excited!",
    "11.20": "I swallowed hard and tried to adjust my position, \nbut \\str[120] held me too tightly,\nmy movements only made us press even closer together.\nMy penis stubbornly pressed between her thighs. \nEven through two layers of fabric,\nher body heat conducted to my nerves like an electric current.",
    "11.21": "\\nl< >\"Eh... \\str[121], down there...\nsomething is pressing against me...\"",
    "11.22": "\\str[120]'s breathing stopped for a moment, \nand my heartbeat skipped a beat.\nThe guilt of being caught made me tremble involuntarily.",
    "11.23": "\\nl< >\"It feels... so hard... and so hot...\n\\str[121] is trembling all over too...\"",
    "11.24": "\\nl< >\"Is, is it because \\str[121] was also scared, \nso, so this happened?\nWhen boys are frightened, they react like this, right?\"",
    "11.25": "\"Eh...? Ah, ah yes...   \\w[30]\nI didn't expect my resistance to horror scenes \nto be so weak either.\"",
    "11.26": "\\str[120] didn't seem angry about it. \nFeeling relieved, my excitement surged again,\nmy penis attempting to swell further, \npressing her soft shorts deeply inward.",
    "11.27": "\\nl< >\"Don't be scared, don't be scared...\nWhen you're afraid, if you just stay closer and feel the warmth, \nyou won't be so scared anymore, right?\"",
    "11.28": "\\str[120] twisted her hips slightly, \ngrinding more tightly against my hardness.\nThen she pulled my hand toward her waistband,\nletting my fingertips hook the edge, as if silently hinting at something.",
    "11.29": "She continued moving her hips, no...   \\w[30]\nI should say she was clearly rubbing against me with that place...  \nBarely managing my frantic breathing, \nmy other hand moved to support her bottom,\nmy fingers hooking into the edge of her shorts, \ntentatively pulling down just a little.",
    "11.30": "Seeing I didn't continue, \n\\str[120] cooperatively lifted her body slightly.\nThis is... permission to continue, \nright?\nI slowly pulled \\str[120]'s shorts down to her knees, \nthen untied the string,\nwatching as her panties gradually slipped off.",
    "11.31": "In a daze, her warm and soft pussy\nwas now pressed directly against my penis without any barrier.",
    "11.32": "\\nl< >\"\\str[121], it's okay now, \nI'll protect you.\"",
    "11.33": "Feeling the moisture there, under \\str[120]'s seductive whisper,\nthe string of my rationality snapped in an instant.\nImmediately after, waves of warmth completely engulfed me.",
    "11.16": "\\str[120]'s voice was intermittent due to nervousness, \nand her body was tense like a fully drawn bowstring.\nBut with slow and steady advancement, \nmy penis still managed to penetrate—\nThe folds within were stretched open layer by layer, \nand the warm, moist inner walls immediately clung tightly.",
    "11.34": "\\str[121]♥\nMmm♥ Ahn♥\nI want... more warmth...♥\nIt feels... so good...♥",
    "11.35": "\"Try moving a bit slower...\"\nI held \\str[120]'s waist, guiding her in a soft voice.     \\w[90]\nShe clumsily slowed down the rhythm of her body.",
    "11.36": "\"Not up and down... try moving back and forth...\"\nI gently pressed her hips, coaxing her.     \\w[90]\n\\str[120] obediently changed her movements.",
    "11.37": "\"Lean your body forward a bit...\"\nI softly guided \\str[120] to adjust her posture.   \\w[90]\nShe compliantly did as told, \nand even innocently quickened the rhythm at her waist.",
    "11.38": "\"Move a bit faster...\"\nI requested of \\str[120] while panting.    \\w[90]\nShe began to move her hips obediently yet awkwardly.",
    "11.39": "In the midst of our intense intimacy, I still couldn't help \nbut reach out to gently stroke \\str[120]'s hair.     \\w[150]\nEven though we were tightly joined at this moment, \nmy thoughts were still the same as always—\nI only wanted to tenderly dote on her, \ncomfort her, and make her feel at ease.",
    "11.40": "I gently combed through her hair, disheveled from sweat.      \\w[150]\n\\str[120] nuzzled against my palm like a kitten, \nand that trust made my heart tighten.",
    "11.41": "I unconsciously patted her head as I usually do.     \\w[150]\n\\str[120] squinted her eyes, both puzzled and content.",
    "11.42": "\"Does it... hurt?\"",
    "11.43": "\\nl< >\"Mm... it hurts a little bit... but...\nI want to make... \\str[121]... feel good...\"",
    "11.44": "\\str[120] looked at me with eyes of absolute trust,\nthat purity made me feel both guilty and intoxicated.",
    "11.45": "\"Do you know what we're doing right now...?\"",
    "11.46": "\\nl< >\"Hm...? Aren't we playing a cuddle game...?\n\\str[121]'s body... is inside me now...♥\"",
    "11.47": "\\str[120] tilted her head, \nspeaking in a tone as casual as everyday conversation.",
    "11.48": "\"Why would you think of doing something like this...?\"",
    "11.49": "\\nl< >\"Because... \\str[121] scared me...\nAnd also... when we're close together like this... \nit's really warm...♥\"",
    "11.50": "\\str[120] answered earnestly with her misguided logic, \na pure smile on her face.",
    "11.9": "I-I'm already reaching my limit...!\nWhat should I do...?!",
    "11.51": "Cum Inside\nCum Outside",
    "11.52": "Feeling the urge to climax growing stronger, \njust before the semen was about to burst forth,\nI held \\str[120] tightly in my arms.",
    "11.53": "Feeling the urge to climax growing stronger, \njust before the semen was about to burst forth,\nI pulled my penis out from inside \\str[120]'s body.",
    "11.54": "At the instant of nearly crossing the line, \nmy body instinctively made a choice——       \\w[40]\nI suddenly withdrew my penis, and the white fluid gushed out,\nleaving traces across her tender skin.",
    "11.55": "The wave of pleasure instantly swallowed my rationality, \nand I had already ejaculated before I could think.   \\w[40]\nThe hot semen was poured entirely deep inside \\str[120]'s body.",
    "11.56": "\\nl< >\"Uweh... my tummy feels all warm... \nlike I drank hot milk.\"",
    "11.57": "\\nl< >\"Mm... I can feel something hot moving around...\nIt's gurgling...\"",
    "11.58": "\\nl< >\"\\str[121]... will this... stay inside forever?\nIs it okay to leave it like this?\"",
    "11.59": "Have a Baby\nGrow a Melon",
    "11.60": "\\nl< >\"A baby...?   \\w[60]\nA baby... between \\str[121] and me...?\"",
    "11.61": "\"That's right, a cute little baby just like you.\"",
    "11.62": "\\nl< >\"I-I don't understand... \nI've never seen a baby before...   \\w[120]\nSince you said so... I'm a bit curious...\"",
    "11.63": "Looking at \\str[120]'s completely unguarded eyes filled \nwith pure curiosity, the urges that had finally subsided\nbegan screaming wildly inside my body again,\nand my softened member quickly regained its vigor.",
    "11.64": "\\nl< >\"Nnh♥ \\str[121]!?\nIt's... it's getting big again...?\"",
    "11.65": "\\nl< >\"Does \\str[121] want to try again too...♥\nI also... want to see that... baby...\"",
    "11.66": "\\nl< >\"Hey, \\str[121]... let's do it one more time♥\"",
    "11.67": "\\nl< >\"Eh?! A w-watermelon?!\nThe round, really big kind... \nwill grow in my tummy?!\"",
    "11.68": "\"yeah... your belly will get super big, \nand you'll have to hold onto walls to walk.\"",
    "11.69": "\\nl< >\"N-no!\nI don't want a watermelon growing in my tummy!!\"",
    "11.70": "\\nl< >\"Waaaaaah—\nI need to pour it out quickly!\"",
    "11.71": "It seems the joke went a bit too far.\n\\str[120] didn't even have time to mind the \nlingering soreness below, and stumbled off of me,\nrushing to the toilet like a startled little rabbit.",
    "11.72": "But seeing her so flustered and panicked was just too cute.\nI became even more curious about how she \nplanned to handle the situation—",
    "11.73": "Go Peek",
    "11.74": "Mm-hmm... can't miss this amusing scene—",
    "11.75": "\\nl< >\"I have to get it all out... sob sob...\"",
    "11.76": "\\nl< >\"Geez, \\str[121]... \nyou’re the one who put it in...\"",
    "11.77": "\\nl< >\"Stupid \\str[121]... why didn't you tell me sooner...\"",
    "11.78": "\\nl< >\"If it really grows... \n\\str[121] has to take responsibility... \nhe have to help me eat it...\"",
    "11.79": "Watching \\str[120] earnestly and pitifully trying to \nexpel the semen from her body,\na strong sense of guilt welled up inside me,\nI should tell her the truth in a bit...",
    "11.80": "It's already very late, \nI can't let \\str[120] exhaust herself like this anymore...\nLet's stop here for today.",
    "11.81": "Ugh, my body... is losing strength...!\nEven though I still want to continue... \nmy stamina is already...\nLet's stop here for today.",
    "11.82": "\\nl< >\"\\str[121], I'm sorry...\nIt's all because I was too cowardly that \nthings got so messy...\"",
    "11.83": "\\nl< >\"Even though the movie was scary, \nbeing able to end up like just now...\nbeing filled up tightly and held tightly by \\str[121]...\nactually felt pretty nice too♥\"",
    "11.84": "\\nl< >\"Next time we have a chance, \nlet's watch the rest of it together♥\"",
    "11.85": "\\nl< >\"Wah♥ That startled me...\nThis white stuff... did it come out from \\str[121]...?\"",
    "11.86": "\\nl< >\"\\str[121]...♥ So much came out...\nIt's gotten all sticky...\"",
    "11.87": "\\str[120] just looked down in surprise \nat the white turbid fluid splashed on her body,\nthen extended her finger, touching those traces that \nstill carried warmth, observing them.",
    "11.88": "\\nl< >\"\\str[121]...♥\nThat feeling just now... of my heart racing...♥\"\nOne more time... okay...?♥",
    "11.89": "\\nl< >\"\\str[121]... is it over already...?♥\nBut... I still want to... \ncuddle with you a bit longer...♥\"",
    "11.90": "Fill Her Up!\nNot This Time",
    "11.91": "Comfort Her",
    "12.0": "...Wait, this looks like R-rated content. \nIs this really okay? Is it really okay for her upbringing \nto let \\str[120] watch this!?",
    "12.1": "\\nl< >\"\\str[121]? What's wrong?\nAren't we going to watch the movie?\"",
    "12.2": "\"Ah... there's been a little accident.\nI'm debating whether we should watch it or not...\"",
    "12.3": "\\nl< >\"Can’t I watch it? What kind of movie is it?\"",
    "12.4": "A lewd movie\n\\fs[20]A movie for bad girl",
    "12.5": "\\nl< >\"L-lewd...? \nIs it something only adults are allowed to see?\nI don't really understand it, but is it... \nbad to watch it now...?\"",
    "12.6": "Despite saying it might be bad, \nshe didn't show any sign of resistance.\nShe just restlessly wiggled her toes and \nstole glances at my expression.",
    "12.7": "Being exposed to the 'adult world' at such a late hour\nseemed to make her feel both confused and faintly excited.",
    "12.8": "\\nl< >\"Lewd... is it really lewd...?\nWhy do you even have something like that, \\str[121]...?\"",
    "12.9": "\\nl< >\"But... if it's just a little bit...\nI guess it's okay... \nif you really want to watch it that badly, \\str[121].\"",
    "12.10": "Even though she spoke as if she were just doing me a favor,\nshe had already quietly shimmied closer to me.\nHer eyes flickered toward me every now and then, \nas if checking for my reaction.",
    "12.11": "\\nl< >\"Eh...? Then, after watching it... \nwill I become a bad girl?\nWill I get punished too?\"",
    "12.12": "\\nl< >\"If \\str[121] can watch it, \nI should be able to watch it too, right...?   \\}\nWatching it in secret like this...\"",
    "12.13": "Her curiosity seemed to have been piqued. \nAlthough she immediately covered her eyes with her hands,\nI could clearly see her eyes peeking through the gaps  \nin her fingers, staring intently at the TV screen.",
    "12.14": "\\nl< >\"B-bad girl... are you talking about me, \\str[121]?\nThis is all \\str[121]'s fault anyway...!\"",
    "12.15": "She puffed out her cheeks and stretched out her small feet, \npoking my leg with her toes every now and then.\nThe pressure was soft and lacked any real force. rather than a protest,\nit felt more like she was acting spoiled and petulant.",
    "12.16": "\"Alright, I'm just kidding. \nI really want to watch it.\nSo, will you just keep me company?\"",
    "12.17": "Reading between the lines of her reaction,\nI walked to the TV with the tape and slid it into the VCR.",
    "12.18": "\\nl< >\"Since you put it that way... \nI guess I have no choice but to stay with you.\nIf... if there are any scenes that are too weird,\nyou have to tell me in advance, okay...!\"",
    "12.19": "\\str[120] muttered under her breath, \nand taking advantage of her acting spoiled, \nshe timed it perfectly as I sat down, \nstraddling directly onto my lap.",
    "12.20": "As if trying to hide herself, \nshe clung tightly to my chest and gripped my arms firmly,\nseemingly trying to mask the sound of her racing heartbeat.",
    "12.21": "\\nl< >\"Ehehe... \\str[121]’s special seat~!\"",
    "12.22": "\\c[27]\"Hey... ▓▓▓▓, if the gods saw us doing this...\nwould we be cast into hell?\"",
    "12.23": "\\c[27]\"...Hmph. As long as I'm with you,\nI don't care even if it's hell.\"",
    "12.24": "\\c[27]\"Uuu... Me too...\nI don't want to be just a ▓▓▓▓ anymore...!\"",
    "12.25": "\\c[27](Voice-over: And so, they fell in love and \nbegan a sex session lasting 2 hours and 14 minutes—)",
    "12.26": "\"I-It's so big... I'm gonna be broken...!\n▓▓▓▓'s thing... it's churning my insides to mush...!!\nAaaaahhh! Haaah! Haaah! ♥\"",
    "12.27": "...This is hopeless. No matter how you look at it, \nthis is just a low-budget, trashy adult flick.\nThe acting is so hammy it's laughable, and the budget was clearly \nblown entirely on the late-stage, uninspired erotic scenes...  \n\\{Come to think of it, is the rest of the  \nprogress bar really all this kind of content?!",
    "12.28": "And it just had to be such an awkward theme...\nLetting \\str[120] see something like this... \nit must be quite a shock for her.",
    "12.29": "I quickly grabbed the remote and turned down the volume to \nstop those soulless, dry groans from harassing our ears further.\nWhen I looked beside me with concern, \nI realized \\str[120] was already looking quite shaken.",
    "12.30": "Sssssss!\n\\w[30]\\^",
    "12.31": "No matter how dense she might be about the birds and the bees, \nseeing such explicit images on TV,\n\\str[120] finally realized just how shameful \nthe content she was watching really was.\nHer cheeks instantly turned crimson, \nas if I could hear the sound of steam erupting from her head.",
    "12.32": "\\nl< >\"I-Is that... is that what it's like...     \\w[120]\nto do... lewd things?\"",
    "12.33": "My shaken \\str[120] began to stammer, \nyet her eyes remained glued to the screen, unmoving.",
    "12.34": "\"Yeah... if it's too much for you, we should—\"",
    "12.35": "\\nl< >\"I-I'm fine! You're always...                    \\w[120]\nplaying with my body anyway... Something like this...   \\w[120]\nI-I've been prepared for it for a long time!!\"",
    "12.36": "\\nl< >\"It's you, \\str[121]...!      \\w[120]\nAfter seeing this... you're not...     \\w[120]\nthinking of some bad ideas to bully me again, are you...!\"",
    "12.37": "As if trying to embolden herself, she deliberately \npuffed out her chest, squirming restlessly in my arms. \nThe soft, elastic sensation against my thighs\nmade me catch my breath sharply.",
    "12.38": "Ho... this girl. Not only has she learned to talk tough,\nshe's even started to counterattack unconsciously—\nWell, if you're going that far, how about this~?",
    "12.39": "\"You're right. Seeing them go at it so intensely on TV,\nmy own body really wants to give it a serious try too—\"",
    "12.39.5": "Lift Camisole",
    "12.40": "Before she could even react, I slid up her thin camisole.\nLiberated from their constraints, her plump, snowy breasts \nbounced lightly in the air as the fabric pulled away.",
    "12.40.1": "\\nl< >\"...Eh!? \\str[121]...        \\w[120]\nyou're already unable to hold back...!?\"",
    "12.40.2": "Though startled by this sudden attack,\nshe didn't flee in panic as she usually would. \nInstead, her breathing simply grew more ragged.",
    "12.40.3": "Her gasps gradually overlapped and resonated \nwith the moans coming from the TV,\nand the air instantly became scorched and thick with tension.",
    "12.40.4": "\"Are you still so curious about what \nhappens next in the movie, even like this...?\nIt seems \\str[120] is becoming quite a lewd girl...\"",
    "12.40.5": "\\nl< >\"L-Lewd...?                \\w[120]\n\\str[121], do you... hate lewd girls...?\"",
    "12.40.6": "The current scorching, \nambiguous atmosphere compelled her to silently endure\nthat strange excitement welling up from \ndeep within her body, despite her shame.",
    "12.40.7": "\"As long as it's you, \nI'll love you no matter how you are...\nIf anything, the way you are now... \nyou're so cute I can barely contain myself.\"",
    "12.40.8": "My hands began to wander slowly over her exposed skin,\nfeeling the warmth and elasticity that \nonly intensified as her body heat rose.",
    "12.40.9": "\"So, do you want to try it for yourself...\nthat pleasurable feeling, just like in the movie?\"",
    "12.41": "\\nl< >\"I-I don't know...    \\w[120]\nRight now, I feel like...    \\w[120]\nI can't say no to you...\"",
    "12.41.1": "\\nl< >\"But... the girl on TV             \\w[120]\nlooked like she was feeling so good...    \\w[120]\nI'm a little... curious about that feeling...\"",
    "12.41.2": "Seeing her innocent display, \nthe fire of my lust was finally stoked into a blaze.\nMy wandering hands slid down her waist toward \nthe edge of her shortpants.\nWith a slight rustle, \nthe fabric covering her private parts fell away in an instant.",
    "12.41.3": "\\nl< >\"Ugh...! \\str[121]...            \\w[120]\nit's gotten all sticky down there...\"",
    "12.41.4": "The moment her panties came off, \n\\str[120] was shocked to find a shimmering,\ntransparent thread stretching between her body and the fabric.\nHer already flushed cheeks looked ready to burst into tears of panic.",
    "12.41.5": "\"It's okay, you're not sick...\nit just means your body is being honest \nand is already longing for me.",
    "12.41.6": "\\nl< >\"L-Longing? This place...      \\w[120]\nit already wants you this much...?     \\w[120]\nNext... are you going to...            \\w[120]\nkeep bullying me just like in the movie?\"",
    "12.41.7": "Her voice was no longer filled \nwith her previous shame and unease.\nin its place was a thick, heavy longing. \n \nTo answer that expectation, \nI hooked her under the knees, lifting her crotch high \nand exposing her completely under the bright light.",
    "12.41.8": "\\nl< >\"...Kyaa~!\nT-This position... it's so embarrassing...\"",
    "12.41.9": "Suddenly forced into a humiliating pose, as if \nshe were about to relieve herself right in front of me,\nshe instinctively tried to press her legs together. \n \nBut my hands held her firmly in place,\nleaving her tiny body to do nothing but tremble helplessly.",
    "12.42": "\\nl< >\"Uuueeee... \\str[121], you're so mean...   \\w[120]\nWhy... am I the only one who's been stripped bare...\"",
    "12.43": "She let out a weak, whimpering sound like a small animal.\nThis display of utter submission mixed with spoiled dependence\nconstantly stimulated my dark urge to \nruthlessly tease and cherish her.",
    "12.44": "But my cock was already engorged with excitement, \nand her sweet spot was already drenched...\nThe arrow is on the string. \nour patience has reached its limit!",
    "12.45": "I quickly shed my own pants,\npressing my throbbing, thick rod against her and rubbing it slowly.",
    "12.46": "\\nl< >\"I-Is this... your thing, \\str[121]...?       \\w[120]\nIt feels... even bigger than the one I just saw on TV...\"",
    "12.47": "Insert into pussy\nInsert into ass",
    "12.48": "Sensing my intent to enter, \n\\str[120] lowered her head slightly,\nstaring intently at the thick, heat-radiating cock\nthat was already pressed against her tender entrance.",
    "12.49": "\\nl< >\"I—I’m ready now…        \\w[180]\\{\nP-please… go ahead!\"",
    "12.50": "As if throwing all caution to the wind, \n\\str[120] let out a clumsy declaration.",
    "12.51": "\"It might hurt a little... if it's too much,\nyou have to tell me, okay?\"",
    "12.52": "\\nl< >\"Mmh... it's okay... \nI-I'll try my best to endure it...!\"",
    "12.53": "Her voice was still tense, her right hand aimlessly stroking my cheek.\nFeeling my shaft swell even more with excitement, \nI decided to let go of the tension in my arms,\nletting her body slowly sink down—",
    "12.54": "\\nl< >\"Ngh—Hngh~~~~!♥\"",
    "12.55": "Driven by the gravity of her falling body,\nthe thick rod forced open that narrow, wet path,\npiercing straight through to her deepest depths.\n \nThe impact of being so completely filled made her\nlet out a dazed moan, her entire frame tightening\nfrom the intense sensation of the intrusion.",
    "12.56": "But she soon began to adapt to the presence inside her, \neven instinctively contracting her muscles.\nThe way she looked—eyes teary from the pain of being stretched, \nyet instinctively yielding— was incredibly erotic.",
    "12.57": "\\nl< >\"Haa... ngh... ♥      \\w[120]\n\\str[121]... is it...        \\w[120]\nenough just to be joined like this...?\"",
    "12.58": "Seemingly thinking it was over, \nshe simply snuggled into my arms,\nher small feet dangling in the air, \nswaying gently with unease.\nI began to exert force with my arms, \ncarefully guiding her body up and down,\nletting my cock slide continuously inside her.",
    "12.59": "\\nl< >\"Kyaa ♥ \\str[121]...!?\nIt... it's moving inside... ♥\nUgh... hngh... ♥\"",
    "12.60": "The sudden movement cut off her innocent question as a \nnever-before-felt tingling sensation swept through her entire body.\nSince her legs were dangling, \nher entire weight was entrusted to my arms.\nWith no strength left to resist, \nshe could only let me control the rhythm, \nletting out one sweet gasp after another.",
    "12.61": "To ease her tension and check her condition,\nI leaned in close to her flushed ear and whispered teasingly.",
    "12.62": "\"Good girl... it doesn't hurt anymore, right?\nTell me... how does it feel now?\"",
    "12.63": "\"And... what about now?\nIs it feeling all warm inside your tummy?\"",
    "12.64": "\"You're doing so well...\nYour body is starting to feel good, isn't it?\"",
    "12.65": "\\nl< >\"Ugh... mm... it doesn't hurt much anymore... ♥\nBut, it's so strange... that part of you, \nit feels like it's filling me up...\nIt feels all tingly inside... and a little itchy... ugh... ♥\"",
    "12.66": "\\nl< >\"Mgh... hngh... it doesn't hurt anymore... ♥\nBut, I feel... my tummy is getting so heavy... ♥\nI'm... I'm already filled up by \\str[121]... ♥\"",
    "12.67": "\\nl< >\"Mgh... mm... ♥ It's so hot inside...\nIt feels like... something really hot is \nswirling around in there... ♥\"",
    "12.68": "\\nl< >\"Haa... hah... ♥ \\str[121], slower... please...\nIt feels like warm little fish are swimming inside me... ugh... ♥\"",
    "12.69": "\\nl< >\"Kyaa ♥ \\str[121]... there... ugh... ♥\nIt's... it's getting so weird... \nI... I can't think anymore... ♥\"",
    "12.70": "\\nl< >\"Hah... ah ♥ Mgh, mgh...! ♥\nEverything is going white... I'm... ngh...\nI-I'm going to melt... mgh... haa... hah... ♥\"",
    "12.71": "\\str[120] pulled her neck back in confusion,\nbut her body, beginning to heat up from the pleasure, \nalready gave the most honest answer.",
    "12.72": "Hearing her soft, \nsweet response filled with pleasure, \nI began to quicken the pace.\n \nWith her legs completely dangling and without support, \nshe could only lean back helplessly,\nher whole body jolting violently with my movements.",
    "12.73": "She had fallen into a completely dazed state, \neyes staring vacantly ahead,\nher dangling toes curling tightly from the intense stimulation.",
    "12.74": "Feeling the rounded touch of her bottom, \nI felt a sudden impulse to try her backdoor.\nFor her, this might be a completely new experience... right?",
    "12.75": "\\nl< >\"Eh...!? Um... \\str[121]... not there...\nIsn't that place just for... when I have to go...?\nI feel like... it would be so messy and gross.\nWhy... would you want to touch a place like that...?\"",
    "12.76": "Sensing me probing toward her backside, \n\\str[120] tensed her shoulders in confusion. \nShe simply had no idea that even a place like that \ncould be cherished and made love to as well.",
    "12.77": "It seems this kind of play is still too early for her...\nI suppressed the urge and decided not to force it.",
    "13.1": "\\nl< >\"Haa... ngh... ♥                    \\w[60]\n\\str[121]... \\str[121]... my tummy...    \\w[60]\nit's being filled up... ♥\"",
    "13.2": "\"Sorry... I guess I was too rough after all...\nIs there anywhere that feels uncomfortable?\"",
    "13.3": "\\nl< >\"No... you know... \\str[121], you're very gentle...    \\w[60]\nBeing able to experience this... is also                       \\w[60]\nthanks to the medicine \\str[121] brought back...\"",
    "13.4": "\\nl< >\"Even though... \\str[121] is still working so hard for me...   \\w[60]\nI feel like... I can't do anything in return...\"",
    "13.5": "\\nl< >\"So, if this..                   \\w[60]\ncan make \\str[121] feel relaxed...      \\w[60]\nno matter how many times... \nI want to give it to you... ♥\"",
    "13.6": "\\nl< >\"Even though... \\str[121], at times like this...    \\w[60]\nyou always tease and bully me on purpose...                 \\w[60]\nbut... \\str[121] is \\str[121]...\"",
    "13.7": "\\nl< >\\}\"You are... my...    \\w[60]\none and only...                \\w[60]\nin the whole world...\"",
    "13.8": "\\str[120]'s voice grew weaker and weaker, \nfollowed by the sound of her steady, even breathing in my ear.\nI knew that her already fragile stamina had reached its limit.",
    "13.9": "Even though Elixir Rubrum is already taking effect in her body,\npushing her any further would be going too far after all...\n \n \nSo, maintaining this awkward, joined position, \nI gently picked up \\str[120],\nand carefully left the living room.",
    "13.10": "Though it was still early, \nseeing \\str[120]'s body trembling slightly in my arms,\nI forcibly suppressed my lingering desire.",
    "13.11": "Watching her frail frame quiver against me, \nmy cock finally went soft.\nit was time to call it a day.",
    "13.12": "The trashy plot on the TV droned on regardless;\neven with the volume lowered, \nit felt piercingly loud in the silence.\nI fumbled for the remote and decisively hit the power button—",
    "13.13": "\\nl< >\"The movie... we haven't finished it...\n \\str[121]...\"",
    "13.14": "\"That's enough for today.\nYour body is already at its limit.\nrest is far more important than any movie—\"",
    "13.15": "\\nl< >\"...Mmh♥\nNext time... let's watch it together again...♥\"",
    "14.0": "Now that \\str[120] has developed a deep curiosity about the adult world,\ngiving her a chance to try this as well would surely \nbe an unprecedented experience for her, wouldn't it?\n...Just thinking about it makes me feel like I can hardly contain myself.",
    "14.1": "Even though \\str[120] has experienced the taste of intercourse, \nfor someone as consistently well-behaved and innocent as her,\nthe idea that a place like this could be used for pleasure was \nclearly far beyond the reach of her little mind's comprehension.",
    "14.2": "\"Actually, that's an extremely sensitive spot \nthat can feel really good, too.\nIf you don't try it, you'll be missing out on \nsome incredible sensations.\"",
    "14.3": "\\nl< >\"It feels good...? You're lying...\nThere's no way that place could feel like that...\nIt's... it's just the place where I go to the toilet, \nhow could it possibly... ugh...\"",
    "14.4": "\"It's true, you know? \nWeren't you just wondering why the people on TV sounded so happy?\nThe human body is full of hidden switches that even \nyou don't know about...\"",
    "14.5": "\\nl< >\"Ugh... if \\str[121] says so...\nThen... I'll give it a small try...\nBut you have to be very gentle, okay?\nIf it feels too weird, you have to stop immediately...!\"",
    "14.6": "Seeing that \\str[120] had no more resistance,\nI reached out my finger, gathered a generous amount of \nclear love juice from her messy pussy,\nand smeared it over the folds of her still tightly closed anus.",
    "14.7": "\\nl< >\"Ugh... ah... hah...\n\\str[121], is this... is this really how it's done...?\nEverything feels so strange right now...\"",
    "14.8": "This never-before-experienced anal massage \nmade \\str[120] squirm uneasily, \nher butt reflexively tightening under my control.\n \nAmidst these waves of inexperienced muscle spasms, \nmy fingertip slowly broke through the resistance, \nprobing bit by bit into the depths.",
    "14.9": "\"Don't be afraid, I'll be very gentle...\nI'm just going in a tiny bit to help you get used to it.\"",
    "14.10": "After managing to stretch her to a depth of two fingers, \nI felt the timing was right,\nand I moved to press my already engorged, \nerect cock against her back door.",
    "14.11": "\\nl< >\"Mmmgh—!! It hurts, it hurts so much...!!\n\\str[121]...!? Stop... it's going to tear... waaaah...!\"",
    "14.12": "Being an entirely undeveloped forbidden zone, \nthe tightness was like an impenetrable wall of iron.\n \n \nEven with the lubrication of her juices, \nthe massive cock could only squeeze in a small fraction \nbefore it couldn't be pushed any further.",
    "14.13": "The intense resistance caused me a wave of dull pain,\nand \\str[120] was in tears from the agony, \nher previously flushed little face instantly turning pale.",
    "14.14": "\"I'm sorry...! \nIt's my fault, I won't do it there anymore...\nGood girl, I didn't hurt you too bad, did I?\"",
    "14.15": "I quickly pulled my cock out from the already \nsomewhat swollen narrow slit, and \\str[120], \nfinally set free, struggled to jump down off me.",
    "14.16": "\\nl< >\"Waaah... waaaah... \\str[121] is an idiot...!\nThat didn't feel good at all...!\"",
    "14.17": "Still sobbing, \\str[120] clutched her aching butt and \nstumbled out of the living room, hiding in her own room.",
    "14.18": "It seems like trying to force this kind of development \nwas a bit too much for the current \\str[120]...\nIf I want to try this style of play, \nI'll need to do much more preparation beforehand...",
    "14.30": "With a practiced touch, I gathered a generous amount of slick \nlove juice from her pussy and spread it evenly over the folds of her anus—\nwhich was no longer tightly shut, instead showing a faint, \ninviting flush.",
    "14.31": "There was no need for a forceful expansion. \nwith a gentle flick of my fingertip along the folds,\nI sank effortlessly into the warm depths.",
    "14.32": "All the effort put into her development lately hadn't gone to waste.\nAs my cock pressed against her, \nher rear began to contract with joyful anticipation.\n \nWithout hesitation, \nI used the downward force of her body's weight to \ndrive my entire length inside—",
    "14.33": "\\nl< >\"Mngh—!! Mmm...♥ \nIt's in...! It really... swallowed all of it...!\"",
    "14.34": "\\nl< >\"Can my butt... \nreally fit something this big inside...?\nSuch a strange feeling... \nmy tummy is being filled to the brim by \\str[121]♥\"",
    "14.35": "Although \\str[120]'s voice still trembled with the lingering discomfort,\nthe initial agony was nowhere to be found on her flushed little face.\nIn its place was the dazed afterglow that follows a forceful awakening.",
    "14.36": "The intense tightness of her anal passage had me surging with excitement. \nNow that she had adjusted, I gripped her thighs firmly with both hands \nand began to drive her body in a relentless up-and-down rhythm.",
    "14.37": "\\nl< >\"Ugh... ah...♥ \n\\str[121]... s-slow down...\nYou're going to... break my insides... uu-wuu♥\"",
    "14.38": "After all, this was a body that had been developed many times over.\nAs my cock thrust in, her anus unfolded smoothly, \nas if consciously and proactively swallowing the entire shaft \ninto its deepest reaches.",
    "14.39": "Every time I thrust upward and let her body drop back down \nwith the full force of gravity, the sensation of the impact \nreaching deep into her abdomen sent \\str[120] into \nfits of breathless, dazed moaning.",
    "14.40": "And it seems \\str[120] has discovered the secret to fighting back.\nEvery time her body drops, she reflexively clinches her buttocks,\ntightly suctioning onto my cock to resist the impact.",
    "14.41": "In this strange interaction, it feels as if my cock is \nbeing frantically sucked by countless tiny suckers.\nThis tightness, which feels like it could drain my very soul, gives me \nthe illusion that I'll be sucked in and rendered completely unable to move.",
    "14.42": "\\nl< >\"Mngh... ah...♥ \nEven though it's such a shameful place...\n\\str[121] is making a complete mess of it right now...♥\"",
    "14.43": "\\nl< >\"My butt clearly wasn't meant for things like this...\nBut this feeling of being stuffed so full... \nit feels so satisfying...♥\"",
    "14.44": "\"That just shows how honest your body is, \\str[120].\nLook, this place is desperately biting down on me and won't let go.\nYou actually want me to stay inside forever, don't you?\"",
    "14.45": "Looking at \\str[120]'s dazed expression and flushed face,\nI teased her while further picking up the pace of my thrusts.",
    "14.46": "To be honest, I was nearing my limit as well.\nThe unreasonable, rhythmic contractions of her anal walls \nwere making my scalp tingle. If I didn't keep moving, \nher butt would literally suck me in and pin me in place!",
    "14.47": "\\nl< >\"It's... it's all \\str[121]'s fault...♥\nTurning me into a bad girl... \nand then saying things like that...♥\nThis is... my revenge on you♥\"",
    "14.48": "\"O-ohhh...!? W-wait...!\"",
    "14.49": "\\str[120] suddenly and proactively clenched her buttocks.\nAn overwhelming suction force erupted from her backdoor instantly.\nNot only did it nearly trap me mid-stroke, but the sudden \nstimulation pushed me to the very brink of climax!",
    "14.50": "\\nl< >\"Ehehe...♥\n\\str[121], your face looks so funny... \nyou're already about to lose it, aren't you?♥\"",
    "14.51": "\\{This little brat...\nShe actually dares to try and tease me now...!\nShe's begging for a thorough correction...!",
    "14.52": "I took a deep breath, \nforcibly suppressing the pleasure about to erupt.\nGripping her thighs with all my strength, \nI began to drive into her butt at full speed.\nThe violent impacts caused the flesh of her buttocks to \nripple in lewd waves.",
    "14.53": "\\nl< >\"Kyaa♥ Ahnn...♥\n\\str[121]!? You're... \nyou're going to stir my insides into a mess...♥\nHow... how can you still be this forceful...♥\"",
    "14.54": "\"Too naive, my little sister!\nIf you think an attack of that level can make me surrender, \nyou've underestimated me!\"",
    "14.55": "\\nl< >\"Ugh♥ Hngh-aaah...♥\nI-I'm sorry... I give up...♥\n\\str[121] is so mean! Stop it... If this keeps up...\nI'm really going to... go crazy! Aaaah♥♥\"",
    "14.56": "Listening to \\str[120]'s unmistakable pleas and moans, \nI launched into the final sprint. The wet slapping sounds of \nour bodies colliding echoed violently through the room,\ncompletely drowning out the sound of the TV nearby.",
    "14.57": "\\nl< >\"Hngh-aaah...♥ Nghh... aaah——\nI'm... I'm going to break~~!\"",
    "14.58": "As \\str[120] spasmed violently from the peak of her climax, \nher anal walls contracting relentlessly, I finally lost all control. \nA thick, scalding torrent of semen erupted like a burst dam,\nsurging deep into her inner reaches.",
    "14.59": "The sheer force of the ejaculation completely overwhelmed her fragile backdoor,\nas a massive amount of white fluid, far too much to be swallowed at once,\noverflowed from the seam of our connection and splashed onto the chair below,\nfilling the room with a shameful, wet sound.",
    "14.60": "That last burst, delivered with every ounce of my strength, \nleft me feeling completely drained.\nUnable to maintain my hold on \\str[120], \nI collapsed limply onto the chair with her.",
    "14.61": "\\str[120]'s body continued to quiver from the afterglow,\nbeads of sweat glistening on her skin under the light.\nOur lower bodies, still joined, twitched occasionally as \nif savoring the lingering stimulation.",
    "14.62": "\\nl< >\"Haa... haah...♥\n\\str[121], you're... you're really the worst...\"",
    "14.63": "\\nl< >\"Even though... I told you to slow down...\nYou just kept going faster and faster instead...\nYou're... so mean... ugh...♥\"",
    "14.64": "\"Wasn't that because you were squeezing me so tight just now?\nLook, you still don't seem to have any intention of letting me go...\"",
    "14.65": "I shifted my hips slightly, \ngiving one last nudge into her depths.\nThis caused her lower abdomen to reflexively contract,\nas she let out a cute gasp at the sudden stimulation.",
    "14.66": "\"Besides, weren't you the one who couldn't \nstop feeling good just a moment ago?\nIt seems your body actually loves me quite a lot, huh? Hehe~\"",
    "14.67": "\\nl< >\"U-ueeegh... I-I don't remember any of that!\nNext time... I absolutely won't let you be so reckless again!\"",
    "14.68": "\\str[120] offered a weak protest, \nbut her body had gone so soft from exhaustion\nthat even raising a hand to push me away was a difficult task.",
    "14.69": "The television on the wall continued playing on its own, \nthe figures on the screen switching between various exaggerated positions.\nWe stayed like that, tightly connected, \nquietly enjoying this moment of tranquility.",
    "14.70": "I’m not sure how much time passed, but the figures on the screen \nfinally reached their finale amidst those intense sounds.\nAs the credits began to roll, \n\\str[120]'s breathing had already become steady and even.",
    "14.71": "\"Hmm... the plot of that tape was pretty trashy,\nbut there were quite a few interesting positions...\nworth learning from.\"",
    "14.72": "\\nl< >\"...Idiot. I'm... completely done for today.\nJust let me... sleep for a little bit... then...\"",
    "14.73": "The clock had already pointed toward the middle of the night.\nExhausted from the intense exercise, \n\\str[120] finally couldn't resist the heavy drowsiness\nand fell fast asleep right there in my arms.",
    "14.74": "\"Yeah... goodnight.\nThere are plenty more tomorrows waiting for us—\""
}